Aggrescan3D-1.0.2.dist-info/DESCRIPTION.rst
Aggrescan3D-1.0.2.dist-info/METADATA
Aggrescan3D-1.0.2.dist-info/RECORD
Aggrescan3D-1.0.2.dist-info/WHEEL
Aggrescan3D-1.0.2.dist-info/entry_points.txt
Aggrescan3D-1.0.2.dist-info/metadata.json
Aggrescan3D-1.0.2.dist-info/top_level.txt
a3d_gui/__init__.py
a3d_gui/__init__.pyc
a3d_gui/create_config.py
a3d_gui/create_config.pyc
a3d_gui/db_manager.py
a3d_gui/db_manager.pyc
a3d_gui/job_handling.py
a3d_gui/job_handling.pyc
a3d_gui/parsePDB.py
a3d_gui/parsePDB.pyc
a3d_gui/requirements.txt
a3d_gui/run_server.py
a3d_gui/run_server.pyc
a3d_gui/server_plot.py
a3d_gui/server_plot.pyc
a3d_gui/utils.py
a3d_gui/utils.pyc
a3d_gui/validators.py
a3d_gui/validators.pyc
a3d_gui/views.py
a3d_gui/views.pyc
a3d_gui/viewsutils.py
a3d_gui/viewsutils.pyc
a3d_gui/.idea/a3dflex.iml
a3d_gui/.idea/misc.xml
a3d_gui/.idea/modules.xml
a3d_gui/.idea/workspace.xml
a3d_gui/computations/.gitfile
a3d_gui/pictures/.gitfile
a3d_gui/static/css/bootstrap-theme.min.css
a3d_gui/static/css/bootstrap.min.css
a3d_gui/static/css/dataTables.bootstrap.css
a3d_gui/static/css/font-awesome.min.css
a3d_gui/static/css/jasny-bootstrap.min.css
a3d_gui/static/css/jquery.dataTables.min.css
a3d_gui/static/css/linechart.css
a3d_gui/static/css/my_custom.css
a3d_gui/static/fonts/FontAwesome.otf
a3d_gui/static/fonts/fontawesome-webfont.eot
a3d_gui/static/fonts/fontawesome-webfont.svg
a3d_gui/static/fonts/fontawesome-webfont.ttf
a3d_gui/static/fonts/fontawesome-webfont.woff
a3d_gui/static/fonts/glyphicons-halflings-regular.eot
a3d_gui/static/fonts/glyphicons-halflings-regular.svg
a3d_gui/static/fonts/glyphicons-halflings-regular.ttf
a3d_gui/static/fonts/glyphicons-halflings-regular.woff
a3d_gui/static/fonts/glyphicons-halflings-regular.woff2
a3d_gui/static/images/Sorting icons.psd
a3d_gui/static/images/back_disabled.png
a3d_gui/static/images/back_enabled.png
a3d_gui/static/images/back_enabled_hover.png
a3d_gui/static/images/favicon.ico
a3d_gui/static/images/forward_disabled.png
a3d_gui/static/images/forward_enabled.png
a3d_gui/static/images/forward_enabled_hover.png
a3d_gui/static/images/sort_asc.png
a3d_gui/static/images/sort_asc_disabled.png
a3d_gui/static/images/sort_both.png
